jumpstarter_driver_http_power/__init__.py
jumpstarter_driver_http_power/driver.py
jumpstarter_driver_http_power/driver_test.py
jumpstarter_driver_http_power-0.7.4.dist-info/METADATA
jumpstarter_driver_http_power-0.7.4.dist-info/WHEEL
jumpstarter_driver_http_power-0.7.4.dist-info/RECORD
